setup.cfg
setup.py
crudit/__init__.py
crudit/exceptions.py
crudit/version.py
crudit.egg-info/PKG-INFO
crudit.egg-info/SOURCES.txt
crudit.egg-info/dependency_links.txt
crudit.egg-info/requires.txt
crudit.egg-info/top_level.txt