Metadata-Version: 1.1
Name: crudit
Version: 0.2.0
Summary: A CRUD framework
Home-page: https://github.com/dutradda/crudit
Author: Diogo Dutra
Author-email: dutradda@gmail.com
License: Apache 2.0
Download-URL: http://github.com/dutradda/crudit/archive/master.zip
Keywords: crud framework sqlalchemy redis elasticsearch
Platform: UNKNOWN
Classifier: Development Status :: 2 - Pre-Alpha
Classifier: Intended Audience :: Developers
Classifier: License :: OSI Approved :: Apache Software License
Classifier: Natural Language :: English
Classifier: Programming Language :: Python :: 2.7
Classifier: Programming Language :: Python :: 3.5
Classifier: Topic :: Database
Classifier: Topic :: Software Development :: Libraries :: Python Modules
